lind_static_resources/__init__.py
lind_static_resources/_version.py
lind_static_resources/factorial/2**10-3.csv
lind_static_resources/factorial/2**10-4.csv
lind_static_resources/factorial/2**10-5.csv
lind_static_resources/factorial/2**10-6.csv
lind_static_resources/factorial/2**11-4.csv
lind_static_resources/factorial/2**11-5.csv
lind_static_resources/factorial/2**11-6.csv
lind_static_resources/factorial/2**11-7.csv
lind_static_resources/factorial/2**15-11.csv
lind_static_resources/factorial/2**3-1.csv
lind_static_resources/factorial/2**31-26.csv
lind_static_resources/factorial/2**4-1.csv
lind_static_resources/factorial/2**5-1.csv
lind_static_resources/factorial/2**5-2.csv
lind_static_resources/factorial/2**6-1.csv
lind_static_resources/factorial/2**6-2.csv
lind_static_resources/factorial/2**6-3.csv
lind_static_resources/factorial/2**7-1.csv
lind_static_resources/factorial/2**7-2.csv
lind_static_resources/factorial/2**7-3.csv
lind_static_resources/factorial/2**7-4.csv
lind_static_resources/factorial/2**8-1.csv
lind_static_resources/factorial/2**8-2.csv
lind_static_resources/factorial/2**8-3.csv
lind_static_resources/factorial/2**8-4.csv
lind_static_resources/factorial/2**9-2.csv
lind_static_resources/factorial/2**9-3.csv
lind_static_resources/factorial/2**9-4.csv
lind_static_resources/factorial/2**9-5.csv
lind_static_resources/factorial/toc.csv
lind_static_resources/plackett_burman/12.csv
lind_static_resources/plackett_burman/16.csv
lind_static_resources/plackett_burman/20.csv
lind_static_resources/plackett_burman/24.csv
lind_static_resources/plackett_burman/28.csv
lind_static_resources/plackett_burman/32.csv
lind_static_resources/plackett_burman/36.csv
lind_static_resources/plackett_burman/4.csv
lind_static_resources/plackett_burman/40.csv
lind_static_resources/plackett_burman/44.csv
lind_static_resources/plackett_burman/48.csv
lind_static_resources/plackett_burman/8.csv
lind_static_resources-0.0.6.dist-info/LICENSE.md
lind_static_resources-0.0.6.dist-info/METADATA
lind_static_resources-0.0.6.dist-info/WHEEL
lind_static_resources-0.0.6.dist-info/top_level.txt
lind_static_resources-0.0.6.dist-info/RECORD
