Metadata-Version: 2.1
Name: lind-static-resources
Version: 0.0.6
Summary: Static designs supplimental package for experimental             design and analysis.
Home-page: UNKNOWN
Author: James Montgomery
Author-email: jamesoneillmontgomery@gmail.com
License: MIT License
